{
  "cli": {
    "version": ">= 16.8.0",
    "appVersionSource": "remote"
  },
  "build": {
    "development": {
      "developmentClient": true,
      "distribution": "internal",
      "channel": "development"
    },
    "preview": {
      "distribution": "internal",
      "channel": "preview",
      "env": {
        "EXPO_PUBLIC_API_URL": "https://api.dev.heyzack.ai"
      },
      "prebuildCommand": "./prebuild.sh"
    },
    "production": {
      "autoIncrement": true,
      "channel": "production"
    }
  },
  "submit": {
    "production": {}
  }
}
